README.md
setup.py
xxzlib/__init__.py
xxzlib.egg-info/PKG-INFO
xxzlib.egg-info/SOURCES.txt
xxzlib.egg-info/dependency_links.txt
xxzlib.egg-info/top_level.txt
xxzlib/dataScience/__init__.py
xxzlib/dataScience/DSPlot/__init__.py
xxzlib/dataScience/DSPlot/plot3DAxes.py
xxzlib/dataScience/DSPlot/plotDecisionTree.py
xxzlib/dataScience/DSPlot/plotKDTree.py
xxzlib/dataScience/DSPlot/plotKNN.py
xxzlib/dataScience/DSPlot/plotLearningCurve.py
xxzlib/dataScience/DSPlot/plotModulePerformance.py
xxzlib/dataScience/DSPlot/plotScatterGraph.py
xxzlib/dataScience/MakeData/__init__.py
xxzlib/dataScience/MakeData/generateData.py