Metadata-Version: 1.0
Name: xxzlib
Version: 0.0.2
Summary: An feature extraction algorithm
Home-page: UNKNOWN
Author: sniper
Author-email: UNKNOWN
License: MIT Licence
Keywords: pip,FAIH,xxzlib
Platform: any
